Metadata-Version: 2.1
Name: SimpleSave
Version: 1.0.0
Summary: SimpleSave is an easy way to work with data in your Python script. You can save and load your data without much effort or knowledge about any storage method.
Home-page: https://github.com/princessmiku/simplesave
Author: Miku
License: MIT
Keywords: storage,json,share,data,saving,global,local,cache
Classifier: Programming Language :: Python :: 3.11
Requires-Python: >=3.11.0
License-File: LICENSE
